{
    "placement": [
        {
            "operator_id": "0",
            "device_id": "node_5-device_1",
            "node_id": "node_5"
        },
        {
            "operator_id": "1",
            "device_id": "node_5-device_1",
            "node_id": "node_5"
        },
        {
            "operator_id": "7",
            "device_id": "node_5-device_1",
            "node_id": "node_5"
        },
        {
            "operator_id": "8",
            "device_id": "node_5-device_1",
            "node_id": "node_5"
        },
        {
            "operator_id": "2",
            "device_id": "node_5-device_1",
            "node_id": "node_5"
        },
        {
            "operator_id": "9",
            "device_id": "node_5-device_1",
            "node_id": "node_5"
        },
        {
            "operator_id": "3",
            "device_id": "node_5-device_1",
            "node_id": "node_5"
        },
        {
            "operator_id": "10",
            "device_id": "node_5-device_1",
            "node_id": "node_5"
        },
        {
            "operator_id": "4",
            "device_id": "node_5-device_1",
            "node_id": "node_5"
        },
        {
            "operator_id": "11",
            "device_id": "node_5-device_1",
            "node_id": "node_5"
        },
        {
            "operator_id": "5",
            "device_id": "node_5-device_1",
            "node_id": "node_5"
        },
        {
            "operator_id": "12",
            "device_id": "node_5-device_1",
            "node_id": "node_5"
        },
        {
            "operator_id": "6",
            "device_id": "node_5-device_1",
            "node_id": "node_5"
        },
        {
            "operator_id": "13",
            "device_id": "node_5-device_1",
            "node_id": "node_5"
        }
    ],
    "objective": {
        "time": "22.791420749649763",
        "actual_time": "31.52259220189779",
        "power": "3728.860578795607",
        "actual_power": "3442.796276761555",
        "post_time": 4.709991931915283
    }
}